<?xml version="1.0" encoding="UTF-8"?>
<sv:node xmlns:crx="http://www.day.com/crx/1.0" xmlns:mix="http://www.jcp.org/jcr/mix/1.0" xmlns:nt="http://www.jcp.org/jcr/nt/1.0" xmlns:fn="http://www.w3.org/2005/xpath-functions" xmlns:fn_old="http://www.w3.org/2004/10/xpath-functions" xmlns:vlt="http://www.day.com/jcr/vault/1.0" xmlns:xs="http://www.w3.org/2001/XMLSchema" xmlns:jcr="http://www.jcp.org/jcr/1.0" xmlns:sv="http://www.jcp.org/jcr/sv/1.0" xmlns:rep="internal" sv:name="tests_write_manipulation_clone">
  <sv:property sv:name="jcr:primaryType" sv:type="Name">
    <sv:value>nt:unstructured</sv:value>
  </sv:property>
  <sv:node sv:name="testWorkspaceClone">
    <sv:property sv:name="jcr:primaryType" sv:type="Name">
      <sv:value>nt:unstructured</sv:value>
    </sv:property>
    <sv:node sv:name="referenceable">
      <sv:property sv:name="jcr:primaryType" sv:type="Name">
        <sv:value>nt:unstructured</sv:value>
      </sv:property>
      <sv:property sv:name="jcr:mixinTypes" sv:type="Name">
        <sv:value>mix:referenceable</sv:value>
      </sv:property>
      <sv:property sv:name="jcr:uuid" sv:type="String">
        <sv:value>842e61c0-09ab-42a9-87c0-308ccc90e6f6</sv:value>
      </sv:property>
      <sv:property sv:name="foo" sv:type="Name">
        <sv:value>bar_1</sv:value>
      </sv:property>
      <sv:node sv:name="cloneChild">
        <sv:property sv:name="jcr:primaryType" sv:type="Name">
          <sv:value>nt:unstructured</sv:value>
        </sv:property>
        <sv:property sv:name="jcr:mixinTypes" sv:type="Name">
          <sv:value>mix:referenceable</sv:value>
        </sv:property>
        <sv:property sv:name="jcr:uuid" sv:type="String">
          <sv:value>9da62173-d674-4413-87a4-8f538e033021</sv:value>
        </sv:property>
        <sv:property sv:name="fooChild" sv:type="Name">
          <sv:value>barChild</sv:value>
        </sv:property>
      </sv:node>
    </sv:node>
    <sv:node sv:name="referenceableRemoveExisting">
      <sv:property sv:name="jcr:primaryType" sv:type="Name">
        <sv:value>nt:unstructured</sv:value>
      </sv:property>
      <sv:property sv:name="jcr:mixinTypes" sv:type="Name">
        <sv:value>mix:referenceable</sv:value>
      </sv:property>
      <sv:property sv:name="jcr:uuid" sv:type="String">
        <sv:value>091d157f-dfaf-42eb-aedd-88183ff8fa3d</sv:value>
      </sv:property>
      <sv:property sv:name="foo" sv:type="Name">
        <sv:value>bar_2</sv:value>
      </sv:property>
    </sv:node>
    <sv:node sv:name="referenceableNoRemoveExisting_1">
      <sv:property sv:name="jcr:primaryType" sv:type="Name">
        <sv:value>nt:unstructured</sv:value>
      </sv:property>
      <sv:property sv:name="jcr:mixinTypes" sv:type="Name">
        <sv:value>mix:referenceable</sv:value>
      </sv:property>
      <sv:property sv:name="jcr:uuid" sv:type="String">
        <sv:value>99cce0f7-91fd-4dab-a9ed-ea939981d40b</sv:value>
      </sv:property>
    </sv:node>
    <sv:node sv:name="referenceableNoRemoveExisting_2">
      <sv:property sv:name="jcr:primaryType" sv:type="Name">
        <sv:value>nt:unstructured</sv:value>
      </sv:property>
      <sv:property sv:name="jcr:mixinTypes" sv:type="Name">
        <sv:value>mix:referenceable</sv:value>
      </sv:property>
      <sv:property sv:name="jcr:uuid" sv:type="String">
        <sv:value>471711ef-043b-4692-874b-f634932e79ba</sv:value>
      </sv:property>
    </sv:node>
    <sv:node sv:name="nonReferenceable">
      <sv:property sv:name="jcr:primaryType" sv:type="Name">
        <sv:value>nt:unstructured</sv:value>
      </sv:property>
      <sv:property sv:name="foo" sv:type="Name">
        <sv:value>bar_3</sv:value>
      </sv:property>
    </sv:node>
    <sv:node sv:name="nonReferenceableRemoveExisting">
      <sv:property sv:name="jcr:primaryType" sv:type="Name">
        <sv:value>nt:unstructured</sv:value>
      </sv:property>
      <sv:property sv:name="foo" sv:type="Name">
        <sv:value>bar_4</sv:value>
      </sv:property>
    </sv:node>
    <sv:node sv:name="nonReferenceableNoRemoveExisting">
      <sv:property sv:name="jcr:primaryType" sv:type="Name">
        <sv:value>nt:unstructured</sv:value>
      </sv:property>
    </sv:node>
  </sv:node>
  <sv:node sv:name="testWorkspaceCorrespondingNode">
    <sv:property sv:name="jcr:primaryType" sv:type="Name">
      <sv:value>nt:unstructured</sv:value>
    </sv:property>
    <sv:node sv:name="sourceNode">
      <sv:property sv:name="jcr:mixinTypes" sv:type="Name">
        <sv:value>mix:referenceable</sv:value>
      </sv:property>
      <sv:property sv:name="jcr:primaryType" sv:type="Name">
        <sv:value>nt:unstructured</sv:value>
      </sv:property>
      <sv:property sv:name="jcr:uuid" sv:type="String">
        <sv:value>a64bfa45-d5e1-4bf0-a739-1890da40579d</sv:value>
      </sv:property>
    </sv:node>
  </sv:node>
  <sv:node sv:name="testWorkspaceUpdateNode">
    <sv:property sv:name="jcr:primaryType" sv:type="Name">
      <sv:value>nt:unstructured</sv:value>
    </sv:property>
    <sv:node sv:name="sourceNode">
      <sv:property sv:name="jcr:mixinTypes" sv:type="Name">
        <sv:value>mix:referenceable</sv:value>
      </sv:property>
      <sv:property sv:name="jcr:primaryType" sv:type="Name">
        <sv:value>nt:unstructured</sv:value>
      </sv:property>
      <sv:property sv:name="jcr:uuid" sv:type="String">
        <sv:value>c8996418-3fd9-407c-bfe6-faea6dcfbb40</sv:value>
      </sv:property>
      <sv:property sv:name="foo" sv:type="Name">
        <sv:value>bar_5</sv:value>
      </sv:property>
      <sv:node sv:name="cloneChild">
        <sv:property sv:name="jcr:primaryType" sv:type="Name">
          <sv:value>nt:unstructured</sv:value>
        </sv:property>
        <sv:property sv:name="jcr:mixinTypes" sv:type="Name">
          <sv:value>mix:referenceable</sv:value>
        </sv:property>
        <sv:property sv:name="jcr:uuid" sv:type="String">
          <sv:value>e7683690-0465-4aa8-87c6-f37a67d08469</sv:value>
        </sv:property>
        <sv:property sv:name="fooChild" sv:type="Name">
          <sv:value>barChild</sv:value>
        </sv:property>
      </sv:node>
    </sv:node>
    <sv:node sv:name="updateNoSuchWorkspace">
      <sv:property sv:name="jcr:mixinTypes" sv:type="Name">
        <sv:value>mix:referenceable</sv:value>
      </sv:property>
      <sv:property sv:name="jcr:primaryType" sv:type="Name">
        <sv:value>nt:unstructured</sv:value>
      </sv:property>
      <sv:property sv:name="jcr:uuid" sv:type="String">
        <sv:value>8cd0ab49-1e3d-4b92-bfe4-48bf3e5efdb3</sv:value>
      </sv:property>
      <sv:property sv:name="foo" sv:type="Name">
        <sv:value>bar_5</sv:value>
      </sv:property>
    </sv:node>
    <sv:node sv:name="updateSrcNotFound">
      <sv:property sv:name="jcr:mixinTypes" sv:type="Name">
        <sv:value>mix:referenceable</sv:value>
      </sv:property>
      <sv:property sv:name="jcr:primaryType" sv:type="Name">
        <sv:value>nt:unstructured</sv:value>
      </sv:property>
      <sv:property sv:name="jcr:uuid" sv:type="String">
        <sv:value>1d392bcb-3e49-4f0e-b0af-7c30ab838122</sv:value>
      </sv:property>
      <sv:property sv:name="foo" sv:type="Name">
        <sv:value>bar_6</sv:value>
      </sv:property>
    </sv:node>
  </sv:node>
</sv:node>
